LICENSE
MANIFEST.in
README.txt
dictobj.py
setup.py
dictobj.egg-info/PKG-INFO
dictobj.egg-info/SOURCES.txt
dictobj.egg-info/dependency_links.txt
dictobj.egg-info/top_level.txt